easytypes/__init__.py
easytypes/easytypes_impl.py
easytypes/easytypes_test.py
easytypes-0.5.5.dist-info/LICENSE
easytypes-0.5.5.dist-info/METADATA
easytypes-0.5.5.dist-info/WHEEL
easytypes-0.5.5.dist-info/RECORD
