Metadata-Version: 2.1
Name: easytypes
Version: 0.5.5
Summary: Easy declaration of data structures with runtime type checking
Home-page: https://github.com/e-reim/easytypes
License: Apache-2.0
Author: Reim, Elijah
Author-email: Elijah.Reim@wartsila.com
Requires-Python: >=3.10,<4.0
Classifier: Development Status :: 4 - Beta
Classifier: Intended Audience :: Developers
Classifier: License :: OSI Approved :: Apache Software License
Classifier: Programming Language :: Python
Classifier: Programming Language :: Python :: 3
Classifier: Programming Language :: Python :: 3.10
Classifier: Programming Language :: Python :: 3.11
Classifier: Programming Language :: Python :: 3
Classifier: Programming Language :: Python :: 3.10
Classifier: Programming Language :: Python :: 3.11
Classifier: Programming Language :: Python :: 3.12
Requires-Dist: typeguard (>=3.0.2,<4.0.0)
Project-URL: Repository, https://github.com/e-reim/easytypes
